fivem/__init__.py
fivem/fivem.py
fivem/player.py
fivem/server.py
async_fivem-1.0.2.dist-info/LICENSE
async_fivem-1.0.2.dist-info/WHEEL
async_fivem-1.0.2.dist-info/METADATA
async_fivem-1.0.2.dist-info/RECORD
