Metadata-Version: 2.1
Name: async-fivem
Version: 1.0.2
Summary: Async API for FiveM endpoints
Home-page: https://github.com/makupi/async-fivem
License: GPL-3.0
Author: makubob
Author-email: makupi@icloud.com
Requires-Python: >=3.6,<4.0
Classifier: License :: OSI Approved :: GNU General Public License v3 (GPLv3)
Classifier: Programming Language :: Python :: 3
Classifier: Programming Language :: Python :: 3.6
Classifier: Programming Language :: Python :: 3.7
Classifier: Programming Language :: Python :: 3.8
Requires-Dist: aiohttp
Requires-Dist: toml (>=0.10.0,<0.11.0)
Project-URL: Repository, https://github.com/makupi/async-fivem
